autorepo/__init__.py
autorepo/commands/__init__.py
autorepo/commands/auth.py
autorepo/commands/list.py
autorepo/commands/repo.py
autorepo/utils/__init__.py
autorepo/utils/auth.py
autorepo/utils/config.py
autorepo/utils/list.py
autorepo/utils/repo.py
autorepo-0.1.9.dist-info/LICENSE
autorepo-0.1.9.dist-info/METADATA
autorepo-0.1.9.dist-info/WHEEL
autorepo-0.1.9.dist-info/entry_points.txt
autorepo-0.1.9.dist-info/RECORD
