Metadata-Version: 2.1
Name: autorepo
Version: 0.1.9
Summary: AutoRepo is a simple, cli-based tool for creating github repositories, without leaving your terminal!
Home-page: https://github.com/saahilb-tech/autorepo
License: MIT
Author: SaahilNotSahil
Author-email: saahil_bhavsar@outlook.com
Requires-Python: >=3.11,<4.0
Classifier: Environment :: Console
Classifier: Intended Audience :: Developers
Classifier: License :: OSI Approved :: MIT License
Classifier: Natural Language :: English
Classifier: Programming Language :: Python :: 3
Classifier: Programming Language :: Python :: 3.11
Classifier: Programming Language :: Python :: 3.12
Classifier: Programming Language :: Python :: 3 :: Only
Classifier: Programming Language :: Python :: 3.10
Classifier: Programming Language :: Python :: 3.7
Classifier: Programming Language :: Python :: 3.8
Classifier: Programming Language :: Python :: 3.9
Classifier: Topic :: Software Development :: Version Control :: Git
Classifier: Topic :: Utilities
Requires-Dist: click (>=8.1.7,<9.0.0)
Requires-Dist: pygithub (>=2.1.1,<3.0.0)
Project-URL: Bug Reports, https://github.com/saahilb-tech/autorepo/issues
Project-URL: Funding, https://buymeacoffee.com/saahilb
Project-URL: Repository, https://github.com/saahilb-tech/autorepo
